Metadata-Version: 2.1
Name: ignorify
Version: 0.1.0
Summary: A Python library for filtering files and directories based on patterns.
Home-page: https://github.com/jaerq/ignorify
Author: Jaer Quijivix-Sweeney
Author-email: jaer.q@protonmail.com
License: GPL-3.0
Classifier: Programming Language :: Python :: 3
Classifier: License :: OSI Approved :: GNU General Public License v3 (GPLv3)
Classifier: Operating System :: OS Independent
Requires-Python: >=3.6
